embedded_proto_options_pb2.py
embedded_proto_options_pb2.pyi
kilight/__init__.py
kilight/client/__init__.py
kilight/client/connector.py
kilight/client/const.py
kilight/client/device.py
kilight/client/discovery.py
kilight/client/exceptions.py
kilight/client/models.py
kilight/client/types.py
kilight/client/util.py
kilight/client/cli/__init__.py
kilight/client/cli/__main__.py
kilight/client/cli/config_manager.py
kilight/client/cli/device_manager.py
kilight/client/cli/entrypoint.py
kilight/client/cli/exceptions.py
kilight/client/cli/config/kilight-defaults.ini
kilight/client/cli/config/logging.ini
kilight/protocol/Color_pb2.py
kilight/protocol/Color_pb2.pyi
kilight/protocol/CommandResult_pb2.py
kilight/protocol/CommandResult_pb2.pyi
kilight/protocol/FanState_pb2.py
kilight/protocol/FanState_pb2.pyi
kilight/protocol/GetData_pb2.py
kilight/protocol/GetData_pb2.pyi
kilight/protocol/OutputIdentifier_pb2.py
kilight/protocol/OutputIdentifier_pb2.pyi
kilight/protocol/OutputState_pb2.py
kilight/protocol/OutputState_pb2.pyi
kilight/protocol/Request_pb2.py
kilight/protocol/Request_pb2.pyi
kilight/protocol/Response_pb2.py
kilight/protocol/Response_pb2.pyi
kilight/protocol/SystemInfo_pb2.py
kilight/protocol/SystemInfo_pb2.pyi
kilight/protocol/SystemState_pb2.py
kilight/protocol/SystemState_pb2.pyi
kilight/protocol/SystemTemperatures_pb2.py
kilight/protocol/SystemTemperatures_pb2.pyi
kilight/protocol/VersionInfo_pb2.py
kilight/protocol/VersionInfo_pb2.pyi
kilight/protocol/WriteOutput_pb2.py
kilight/protocol/WriteOutput_pb2.pyi
kilight/protocol/__init__.py
kilight_client-0.4.2.dist-info/licenses/LICENSE
kilight_client-0.4.2.dist-info/METADATA
kilight_client-0.4.2.dist-info/WHEEL
kilight_client-0.4.2.dist-info/entry_points.txt
kilight_client-0.4.2.dist-info/top_level.txt
kilight_client-0.4.2.dist-info/RECORD
