Metadata-Version: 2.4
Name: kilight-client
Version: 0.4.2
Summary: Client library for communicating with KiLight devices.
Author-email: Patrick Lavigne <me@patrick.codes>
License-Expression: GPL-3.0-or-later
Project-URL: repository, https://github.com/ErraticTech/kilight-client
Classifier: Topic :: Home Automation
Classifier: Development Status :: 2 - Pre-Alpha
Classifier: Environment :: Console
Requires-Python: >=3.12
License-File: LICENSE
Requires-Dist: protobuf
Requires-Dist: zeroconf
Provides-Extra: tests
Requires-Dist: pytest; extra == "tests"
Requires-Dist: pytest-asyncio; extra == "tests"
Provides-Extra: release
Requires-Dist: bump-my-version; extra == "release"
Dynamic: license-file
